cut_pursuit/__init__.py
cut_pursuit/cut_pursuit_L2.py
cut_pursuit/cut_pursuit_L2_cpp_replica.py
tests/__init__.py
tests/test_cut_pursuit.py
cut_pursuit_l2-0.1.2.dist-info/LICENSE
cut_pursuit_l2-0.1.2.dist-info/METADATA
cut_pursuit_l2-0.1.2.dist-info/WHEEL
cut_pursuit_l2-0.1.2.dist-info/top_level.txt
cut_pursuit_l2-0.1.2.dist-info/RECORD
